olll.py
olll-1.0.2.dist-info/LICENSE
olll-1.0.2.dist-info/METADATA
olll-1.0.2.dist-info/WHEEL
olll-1.0.2.dist-info/top_level.txt
olll-1.0.2.dist-info/RECORD
