Metadata-Version: 2.1
Name: olll
Version: 1.0.2
Summary: A Python3 implementation of the LLL
Home-page: https://github.com/orisano/olll
Author: orisano
Author-email: owan.orisano@gmail.com
License: MIT
Platform: UNKNOWN
Classifier: Development Status :: 5 - Production/Stable
Classifier: License :: OSI Approved :: MIT License
Classifier: Programming Language :: Python :: 3.6
Classifier: Programming Language :: Python :: 3.7
Classifier: Programming Language :: Python :: 3.8
Classifier: Programming Language :: Python :: 3 :: Only
